Metadata-Version: 1.0
Name: chance-exception-capturer
Version: 0.0.2
Summary: The exception capturer for chancefocus
Home-page: https://gitee.com/QianFuFinancial/chance-exception-capturer.git
Author: Jimin Huang
Author-email: huangjimin@whu.edu.cn
License: MIT
Platform: UNKNOWN
